rldurham/__init__.py
rldurham/bipedal_walker.py
rldurham/version_check.py
rldurham-0.1.1.dist-info/licenses/LICENSE
rldurham-0.1.1.dist-info/METADATA
rldurham-0.1.1.dist-info/WHEEL
rldurham-0.1.1.dist-info/top_level.txt
rldurham-0.1.1.dist-info/RECORD
