Metadata-Version: 2.4
Name: rldurham
Version: 0.1.1
Summary: Python package for the Reinforcement Learning course at Durham University
Home-page: https://github.com/robert-lieck/rldurham
Author: Robert Lieck
Author-email: robert.lieck@durham.ac.uk
Classifier: Programming Language :: Python :: 3
Classifier: License :: OSI Approved :: GNU General Public License v3 (GPLv3)
Classifier: Operating System :: OS Independent
Requires-Python: >=3.8
License-File: LICENSE
Requires-Dist: IPython
Requires-Dist: ipywidgets
Requires-Dist: requests
Requires-Dist: gymnasium[Box2D,atari,other]
Requires-Dist: torch
Requires-Dist: numpy
Requires-Dist: scipy
Requires-Dist: pandas
Requires-Dist: lightning
Dynamic: author
Dynamic: author-email
Dynamic: classifier
Dynamic: description
Dynamic: description-content-type
Dynamic: home-page
Dynamic: license-file
Dynamic: requires-dist
Dynamic: requires-python
Dynamic: summary
